{
  "Name": "troll_vietcong_machinegun",
  "LocalizedName": "#Ent_Troll_DSHK",
  "Faction": "Evil",
  "BloodType": "regular",
  "IsEthereal": false,
  "LooksEthereal": false,
  "Fearless": false,
  "Uncharmable": false,
  "Nonslippery": false,
  "HasFairy": false,
  "CanSeeInvisible": false,
  "Sounds": [],
  "Gibs": [
    {
      "Model": "..\\..\\Models\\Characters\\gib_generic01",
      "Mass": 50,
      "Scale": 2
    },
    {
      "Model": "..\\..\\Models\\Characters\\gib_generic01",
      "Mass": 50,
      "Scale": 2
    },
    {
      "Model": "..\\..\\Models\\Characters\\gib_generic02",
      "Mass": 50,
      "Scale": 2
    },
    {
      "Model": "..\\..\\Models\\Characters\\gib_generic02",
      "Mass": 50,
      "Scale": 2
    },
    {
      "Model": "..\\..\\Models\\Characters\\gib_generic03",
      "Mass": 40,
      "Scale": 1.8
    },
    {
      "Model": "..\\..\\Models\\Characters\\gib_generic03",
      "Mass": 40,
      "Scale": 1.8
    },
    {
      "Model": "..\\..\\Models\\Characters\\gib_generic04",
      "Mass": 40,
      "Scale": 1.8
    },
    {
      "Model": "..\\..\\Models\\Characters\\gib_generic04",
      "Mass": 40,
      "Scale": 1.8
    },
    {
      "Model": "..\\..\\Models\\Characters\\gib_generic05",
      "Mass": 30,
      "Scale": 1.6
    },
    {
      "Model": "..\\..\\Models\\Characters\\gib_generic05",
      "Mass": 30,
      "Scale": 1.6
    },
    {
      "Model": "..\\..\\Models\\Characters\\gib_generic06",
      "Mass": 30,
      "Scale": 1.6
    },
    {
      "Model": "..\\..\\Models\\Characters\\gib_generic06",
      "Mass": 30,
      "Scale": 1.6
    }
  ],
  "Lights": [],
  "MaxHitpoints": 6000,
  "NrOfHealthbars": 1,
  "Undying": false,
  "UndieTime": 0,
  "UndieHitpoints": 6000,
  "PainTolerance": 1600,
  "KnockdownTolerance": 5,
  "ScoreValue": 2000,
  "XPValue": 0,
  "RewardOnKill": true,
  "RewardOnOverkill": true,
  "Regeneration": 100,
  "MaxPanic": 3,
  "ZapModifier": 0,
  "Length": 1.9000001,
  "Radius": 1.3,
  "Mass": 6000,
  "Speed": 4.7,
  "TurnSpeed": 5,
  "BleedRate": 300,
  "StunTime": 2,
  "SummonElementBank": "None",
  "SummonElementCue": "",
  "Resistances": [
    {
      "Element": "Earth",
      "Multiplier": 0.5,
      "Modifier": -30,
      "StatusImmunity": false
    }
  ],
  "Models": [
    {
      "Model": "..\\..\\models\\characters\\troll\\troll_vietcong_mesh_0",
      "Scale": 0.95,
      "Tint": [
        1,
        1,
        1
      ]
    }
  ],
  "AnimationSkeleton": "..\\..\\models\\characters\\troll\\troll_animation_0",
  "Effects": [],
  "Animations": [
    {
      "AnimationClips": [
        {
          "AnimationType": "attack_ranged0",
          "AnimationKey": "rifle_attack0_pilen",
          "AnimationSpeed": 1,
          "BlendTime": 0,
          "Loop": false,
          "AnimationActions": [
            {
              "_ActionType": "Gunfire",
              "WeaponSlot": 0,
              "Accuracy": 1,
              "ActionStart": 0.1714,
              "ActionEnd": 0.857
            }
          ]
        },
        {
          "AnimationType": "attack_ranged1",
          "AnimationKey": "rifle_attack_sweep",
          "AnimationSpeed": 1,
          "BlendTime": 0,
          "Loop": false,
          "AnimationActions": [
            {
              "_ActionType": "Gunfire",
              "WeaponSlot": 0,
              "Accuracy": 0.8,
              "ActionStart": 0.1,
              "ActionEnd": 1
            }
          ]
        },
        {
          "AnimationType": "attack_melee0",
          "AnimationKey": "attack_swipe",
          "AnimationSpeed": 1,
          "BlendTime": 0,
          "Loop": false,
          "AnimationActions": [
            {
              "_ActionType": "DealDamage",
              "WeaponSlot": 0,
              "Target": "All",
              "ActionStart": 0.15,
              "ActionEnd": 0.44
            },
            {
              "_ActionType": "PlaySound",
              "Cue": "chr_troll_war_attack",
              "Bank": "Characters",
              "ActionStart": 0.1,
              "ActionEnd": 0
            }
          ]
        },
        {
          "AnimationType": "attack_melee1",
          "AnimationKey": "attack_kick",
          "AnimationSpeed": 1,
          "BlendTime": 0,
          "Loop": false,
          "AnimationActions": [
            {
              "_ActionType": "DealDamage",
              "WeaponSlot": 1,
              "Target": "All",
              "ActionStart": 0.1,
              "ActionEnd": 0.3
            },
            {
              "_ActionType": "PlaySound",
              "Cue": "chr_troll_war_attack",
              "Bank": "Characters",
              "ActionStart": 0.1,
              "ActionEnd": 0
            },
            {
              "_ActionType": "PlayEffect",
              "Bone": "RightToes",
              "Attached": false,
              "Effect": "troll_kick",
              "Value": -1,
              "ActionStart": 0.3,
              "ActionEnd": 1
            }
          ]
        },
        {
          "AnimationType": "attack_recoil",
          "AnimationKey": "attack_crush_recoil",
          "AnimationSpeed": 1,
          "BlendTime": 0,
          "Loop": false,
          "AnimationActions": []
        },
        {
          "AnimationType": "taunt0",
          "AnimationKey": "twohand_taunt0",
          "AnimationSpeed": 1,
          "BlendTime": 0,
          "Loop": false,
          "AnimationActions": [
            {
              "_ActionType": "PlaySound",
              "Cue": "chr_troll_angry",
              "Bank": "Characters",
              "ActionStart": 0.25,
              "ActionEnd": 0
            },
            {
              "_ActionType": "PlayEffect",
              "Bone": "mouth",
              "Attached": false,
              "Effect": "troll_drool",
              "Value": -1,
              "ActionStart": 0.25,
              "ActionEnd": 0.8
            }
          ]
        },
        {
          "AnimationType": "idle",
          "AnimationKey": "rifle_idle",
          "AnimationSpeed": 1,
          "BlendTime": 0,
          "Loop": true,
          "AnimationActions": []
        },
        {
          "AnimationType": "idle_wnd",
          "AnimationKey": "rifle_idle",
          "AnimationSpeed": 1,
          "BlendTime": 0,
          "Loop": true,
          "AnimationActions": []
        },
        {
          "AnimationType": "idle_agg",
          "AnimationKey": "rifle_idle_agg",
          "AnimationSpeed": 1,
          "BlendTime": 0,
          "Loop": true,
          "AnimationActions": []
        },
        {
          "AnimationType": "idlelong_agg0",
          "AnimationKey": "idlelong_agg",
          "AnimationSpeed": 1,
          "BlendTime": 0,
          "Loop": true,
          "AnimationActions": []
        },
        {
          "AnimationType": "hit",
          "AnimationKey": "rifle_hit",
          "AnimationSpeed": 1,
          "BlendTime": 0,
          "Loop": false,
          "AnimationActions": [
            {
              "_ActionType": "PlaySound",
              "Cue": "chr_troll_war_pain",
              "Bank": "Characters",
              "ActionStart": 0.1,
              "ActionEnd": 0
            }
          ]
        },
        {
          "AnimationType": "hit_fly",
          "AnimationKey": "hit",
          "AnimationSpeed": 1,
          "BlendTime": 0,
          "Loop": true,
          "AnimationActions": []
        },
        {
          "AnimationType": "hit_slide",
          "AnimationKey": "hit",
          "AnimationSpeed": 1,
          "BlendTime": 0,
          "Loop": true,
          "AnimationActions": []
        },
        {
          "AnimationType": "hit_stun_begin",
          "AnimationKey": "land",
          "AnimationSpeed": 1,
          "BlendTime": 0,
          "Loop": false,
          "AnimationActions": []
        },
        {
          "AnimationType": "hit_stun_end",
          "AnimationKey": "knockdown",
          "AnimationSpeed": 1,
          "BlendTime": 0,
          "Loop": false,
          "AnimationActions": []
        },
        {
          "AnimationType": "die0",
          "AnimationKey": "die0",
          "AnimationSpeed": 1,
          "BlendTime": 0,
          "Loop": false,
          "AnimationActions": [
            {
              "_ActionType": "PlayEffect",
              "Bone": "mouth",
              "Attached": false,
              "Effect": "gore_spray_regular",
              "Value": -1,
              "ActionStart": 0,
              "ActionEnd": 0.15
            },
            {
              "_ActionType": "PlayEffect",
              "Bone": "mouth",
              "Attached": false,
              "Effect": "gore_spray_regular",
              "Value": -1,
              "ActionStart": 0.48,
              "ActionEnd": 0.52
            },
            {
              "_ActionType": "PlayEffect",
              "Bone": "mouth",
              "Attached": false,
              "Effect": "gore_spray_regular",
              "Value": -1,
              "ActionStart": 0.7,
              "ActionEnd": 0.95
            },
            {
              "_ActionType": "PlayEffect",
              "Bone": "mouth",
              "Attached": false,
              "Effect": "troll_slam",
              "Value": -1,
              "ActionStart": 0.91,
              "ActionEnd": 1
            },
            {
              "_ActionType": "PlaySound",
              "Cue": "misc_bodyfall_heavy",
              "Bank": "Misc",
              "ActionStart": 0.91,
              "ActionEnd": 0
            },
            {
              "_ActionType": "PlaySound",
              "Cue": "chr_trollstone_vomit",
              "Bank": "Characters",
              "ActionStart": 0,
              "ActionEnd": 0
            },
            {
              "_ActionType": "PlaySound",
              "Cue": "chr_trollstone_vomit",
              "Bank": "Characters",
              "ActionStart": 0.48,
              "ActionEnd": 0
            },
            {
              "_ActionType": "CameraShake",
              "Duration": 0.2,
              "Magnitude": 0.5,
              "ActionStart": 0.91,
              "ActionEnd": 0
            }
          ]
        },
        {
          "AnimationType": "die1",
          "AnimationKey": "die1",
          "AnimationSpeed": 1,
          "BlendTime": 0,
          "Loop": false,
          "AnimationActions": [
            {
              "_ActionType": "PlayEffect",
              "Bone": "mouth",
              "Attached": false,
              "Effect": "gore_spray_regular",
              "Value": -1,
              "ActionStart": 0.15,
              "ActionEnd": 0.5
            },
            {
              "_ActionType": "PlayEffect",
              "Bone": "mouth",
              "Attached": false,
              "Effect": "gore_spray_regular",
              "Value": -1,
              "ActionStart": 0.5,
              "ActionEnd": 0.9
            },
            {
              "_ActionType": "PlayEffect",
              "Bone": "spine1",
              "Attached": false,
              "Effect": "troll_slam",
              "Value": -1,
              "ActionStart": 0.7,
              "ActionEnd": 1
            },
            {
              "_ActionType": "PlaySound",
              "Cue": "chr_troll_war_death",
              "Bank": "Characters",
              "ActionStart": 0,
              "ActionEnd": 0
            },
            {
              "_ActionType": "PlaySound",
              "Cue": "misc_bodyfall_heavy",
              "Bank": "Misc",
              "ActionStart": 0.7,
              "ActionEnd": 0
            },
            {
              "_ActionType": "PlaySound",
              "Cue": "chr_trollstone_vomit",
              "Bank": "Characters",
              "ActionStart": 0,
              "ActionEnd": 0
            },
            {
              "_ActionType": "PlaySound",
              "Cue": "chr_trollstone_vomit",
              "Bank": "Characters",
              "ActionStart": 0.48,
              "ActionEnd": 0
            },
            {
              "_ActionType": "CameraShake",
              "Duration": 0.2,
              "Magnitude": 0.5,
              "ActionStart": 0.7,
              "ActionEnd": 0
            }
          ]
        },
        {
          "AnimationType": "die_drown",
          "AnimationKey": "die_drown",
          "AnimationSpeed": 1,
          "BlendTime": 0,
          "Loop": false,
          "AnimationActions": [
            {
              "_ActionType": "PlaySound",
              "Cue": "chr_troll_drown01",
              "Bank": "Characters",
              "ActionStart": 0,
              "ActionEnd": 0
            },
            {
              "_ActionType": "PlaySound",
              "Cue": "chr_generic_drown02",
              "Bank": "Characters",
              "ActionStart": 0.8,
              "ActionEnd": 0
            }
          ]
        },
        {
          "AnimationType": "move_run",
          "AnimationKey": "rifle_move",
          "AnimationSpeed": 1.2,
          "BlendTime": 0,
          "Loop": true,
          "AnimationActions": [
            {
              "_ActionType": "Footstep",
              "ActionStart": 0.01,
              "ActionEnd": 0
            },
            {
              "_ActionType": "Footstep",
              "ActionStart": 0.5,
              "ActionEnd": 0
            }
          ]
        },
        {
          "AnimationType": "move_walk",
          "AnimationKey": "rifle_move",
          "AnimationSpeed": 1.3,
          "BlendTime": 0,
          "Loop": true,
          "AnimationActions": [
            {
              "_ActionType": "Footstep",
              "ActionStart": 0.01,
              "ActionEnd": 0
            },
            {
              "_ActionType": "Footstep",
              "ActionStart": 0.5,
              "ActionEnd": 0
            }
          ]
        },
        {
          "AnimationType": "move_wnd",
          "AnimationKey": "rifle_move",
          "AnimationSpeed": 1,
          "BlendTime": 0,
          "Loop": true,
          "AnimationActions": []
        },
        {
          "AnimationType": "move_panic",
          "AnimationKey": "rifle_move",
          "AnimationSpeed": 1,
          "BlendTime": 0,
          "Loop": true,
          "AnimationActions": []
        },
        {
          "AnimationType": "move_fall",
          "AnimationKey": "rifle_move",
          "AnimationSpeed": 1,
          "BlendTime": 0,
          "Loop": true,
          "AnimationActions": []
        },
        {
          "AnimationType": "spec_alert0",
          "AnimationKey": "hit",
          "AnimationSpeed": 1,
          "BlendTime": 0,
          "Loop": false,
          "AnimationActions": []
        },
        {
          "AnimationType": "spec_entangled",
          "AnimationKey": "entangled",
          "AnimationSpeed": 1,
          "BlendTime": 0,
          "Loop": true,
          "AnimationActions": []
        },
        {
          "AnimationType": "spec_entangled_attack",
          "AnimationKey": "entangled_attack",
          "AnimationSpeed": 1,
          "BlendTime": 0,
          "Loop": false,
          "AnimationActions": [
            {
              "_ActionType": "BreakFree",
              "Magnitude": 1,
              "WeaponSlot": 0,
              "ActionStart": 0.8,
              "ActionEnd": 0
            }
          ]
        },
        {
          "AnimationType": "spec_action0",
          "AnimationKey": "spec_action_dig",
          "AnimationSpeed": 1,
          "BlendTime": 0,
          "Loop": true,
          "AnimationActions": [
            {
              "_ActionType": "PlaySound",
              "Cue": "chr_troll_war_attack",
              "Bank": "Characters",
              "ActionStart": 0.1,
              "ActionEnd": 0
            },
            {
              "_ActionType": "PlaySound",
              "Cue": "chr_troll_war_attack",
              "Bank": "Characters",
              "ActionStart": 0.7,
              "ActionEnd": 0
            }
          ]
        },
        {
          "AnimationType": "spec_action1",
          "AnimationKey": "ygg_intro",
          "AnimationSpeed": 1,
          "BlendTime": 0,
          "Loop": false,
          "AnimationActions": [
            {
              "_ActionType": "PlaySound",
              "Cue": "chr_trollstone_attack",
              "Bank": "Characters",
              "ActionStart": 0,
              "ActionEnd": 0
            }
          ]
        },
        {
          "AnimationType": "talk_casual0",
          "AnimationKey": "hit",
          "AnimationSpeed": 1.5,
          "BlendTime": 0,
          "Loop": false,
          "AnimationActions": [
            {
              "_ActionType": "PlaySound",
              "Cue": "chr_troll_war_attack",
              "Bank": "Characters",
              "ActionStart": 0.1,
              "ActionEnd": 0
            }
          ]
        }
      ]
    },
    {
      "AnimationClips": []
    },
    {
      "AnimationClips": []
    },
    {
      "AnimationClips": []
    },
    {
      "AnimationClips": []
    },
    {
      "AnimationClips": []
    },
    {
      "AnimationClips": []
    },
    {
      "AnimationClips": []
    },
    {
      "AnimationClips": []
    },
    {
      "AnimationClips": []
    },
    {
      "AnimationClips": []
    },
    {
      "AnimationClips": []
    },
    {
      "AnimationClips": []
    },
    {
      "AnimationClips": []
    },
    {
      "AnimationClips": []
    },
    {
      "AnimationClips": []
    },
    {
      "AnimationClips": []
    },
    {
      "AnimationClips": []
    },
    {
      "AnimationClips": []
    },
    {
      "AnimationClips": []
    },
    {
      "AnimationClips": []
    },
    {
      "AnimationClips": []
    },
    {
      "AnimationClips": []
    },
    {
      "AnimationClips": []
    },
    {
      "AnimationClips": []
    },
    {
      "AnimationClips": []
    },
    {
      "AnimationClips": []
    }
  ],
  "Equipment": [
    {
      "Slot": 0,
      "Bone": "rightattach",
      "Offset": [
        0,
        0,
        0
      ],
      "Item": "..\\items\\NPC\\troll_machinegun_0"
    },
    {
      "Slot": 1,
      "Bone": "rightfootend",
      "Offset": [
        0,
        0,
        0
      ],
      "Item": "..\\items\\NPC\\troll_kick_0"
    }
  ],
  "Conditions": [],
  "AlertRadius": 15,
  "GroupChase": 0,
  "GroupSeperation": 0,
  "GroupCohesion": 0,
  "GroupAlignment": 0,
  "GroupWander": 0,
  "FriendlyAvoidance": 0,
  "EnemyAvoidance": 0,
  "SightAvoidance": 0,
  "DangerAvoidance": 0,
  "AngerWeight": 1,
  "DistanceWeight": 0.5,
  "HealthWeight": 0.1,
  "Flocking": false,
  "BreakFreeStrength": 1,
  "Abilities": [
    {
      "_AbilityType": "Ranged",
      "MinimumRange": 1,
      "MaximumRange": 30,
      "Elevation": 0.87266463,
      "Arc": 0.2617994,
      "Accuracy": 0.4,
      "WeaponSlots": [
        0
      ],
      "Cooldown": 8,
      "AbilityTarget": "Enemy",
      "FuzzyExpression": "distExp(5,30)",
      "Animations": [
        "attack_ranged0"
      ]
    },
    {
      "_AbilityType": "Melee",
      "MinimumRange": 2,
      "MaximumRange": 4,
      "ArcAngle": 0.034906585,
      "WeaponSlots": [
        0
      ],
      "Rotate": false,
      "Cooldown": 5,
      "AbilityTarget": "Enemy",
      "FuzzyExpression": "distexp(0,3)*0.75",
      "Animations": [
        "attack_melee0"
      ]
    },
    {
      "_AbilityType": "Melee",
      "MinimumRange": 0,
      "MaximumRange": 2.5,
      "ArcAngle": 0.17453292,
      "WeaponSlots": [
        0
      ],
      "Rotate": false,
      "Cooldown": 0,
      "AbilityTarget": "Enemy",
      "FuzzyExpression": "distexp(6)*0.5",
      "Animations": [
        "attack_melee1"
      ]
    }
  ],
  "Movement": [],
  "Buffs": [],
  "Auras": []
}