{
  "Name": "staff_smoke",
  "LocalizedName": "#item_vs_staff05",
  "LocalizedDescription": "#item_vs_staff05d",
  "Sounds": [],
  "Grabbable": true,
  "Bound": false,
  "BlockStrength": 0,
  "WeaponClass": "Staff",
  "CooldownTime": 0,
  "HideModel": false,
  "HideEffects": false,
  "PauseSounds": false,
  "Resistances": [],
  "PassiveAbilityType": "None",
  "PassiveAbilityStrength": 0,
  "Effects": [],
  "Lights": [],
  "HasSpecialAbility": true,
  "SpecialAbilityCooldown": 5,
  "SpecialAbility": {
    "Type": "SmokeBomb",
    "Animation": "",
    "Hash": "",
    "Elements": []
  },
  "MeleeRange": 0,
  "MeleeMultihit": false,
  "MeleeConditions": [],
  "RangedRange": 0,
  "Facing": true,
  "Homing": 0,
  "RangedElevation": 0,
  "RangedDanger": 0,
  "GunRange": 0,
  "GunClip": 1,
  "GunRate": 1,
  "GunAccuracy": 1,
  "GunSound": "",
  "GunMuzzleEffect": "",
  "GunShellEffect": "",
  "GunTracerVelocity": 100,
  "GunNonTracer": "",
  "GunTracer": "",
  "GunConditions": [],
  "ProjectileModel": "",
  "RangedConditions": [],
  "Scale": 1,
  "Model": "..\\..\\..\\Models\\Items_Wizard\\smoke_bomb_0",
  "Auras": []
}