{
  "Name": "weapon_woot_humidity_dispenser",
  "LocalizedName": "#woot_item_weapon01",
  "LocalizedDescription": "#woot_item_weapon01d",
  "Sounds": [],
  "Grabbable": true,
  "Bound": false,
  "BlockStrength": 100,
  "WeaponClass": "Handgun",
  "CooldownTime": 0.7,
  "HideModel": false,
  "HideEffects": true,
  "PauseSounds": false,
  "Resistances": [],
  "PassiveAbilityType": "None",
  "PassiveAbilityStrength": 0,
  "Effects": [],
  "Lights": [],
  "HasSpecialAbility": false,
  "SpecialAbilityCooldown": 0,
  "SpecialAbility": null,
  "MeleeRange": 0,
  "MeleeMultihit": false,
  "MeleeConditions": [],
  "RangedRange": 15,
  "Facing": true,
  "Homing": 0,
  "RangedElevation": 0,
  "RangedDanger": 0,
  "GunRange": 0,
  "GunClip": 1,
  "GunRate": 1,
  "GunAccuracy": 1,
  "GunSound": "",
  "GunMuzzleEffect": "",
  "GunShellEffect": "",
  "GunTracerVelocity": 100,
  "GunNonTracer": "",
  "GunTracer": "",
  "GunConditions": [],
  "ProjectileModel": "",
  "RangedConditions": [
    {
      "ConditionType": "Hit",
      "Hitpoints": 0,
      "Element": "All",
      "Threshold": 0,
      "Time": 0,
      "Repeat": true,
      "Events": [
        {
          "_EventType": "Splash",
          "AttackProperty": "Status",
          "Element": "Water",
          "Amount": 100,
          "Magnitude": 1,
          "Radius": 2
        },
        {
          "_EventType": "Effect",
          "Follow": false,
          "WorldAligned": false,
          "Effect": "weapon_woot_humidity_dispenser_water_globe_emit"
        },
        {
          "_EventType": "Sound",
          "Bank": "Additional",
          "Cue": "woot_humidity_hit",
          "Magnitude": 0,
          "StopOnRemove": false
        },
        {
          "_EventType": "Remove",
          "Bounces": 0
        }
      ]
    },
    {
      "ConditionType": "Collision",
      "Hitpoints": 0,
      "Element": "All",
      "Threshold": 0,
      "Time": 0,
      "Repeat": true,
      "Events": [
        {
          "_EventType": "Splash",
          "AttackProperty": "Status",
          "Element": "Water",
          "Amount": 100,
          "Magnitude": 1,
          "Radius": 2
        },
        {
          "_EventType": "Effect",
          "Follow": false,
          "WorldAligned": false,
          "Effect": "weapon_woot_humidity_dispenser_water_globe_emit"
        },
        {
          "_EventType": "Sound",
          "Bank": "Additional",
          "Cue": "woot_humidity_hit",
          "Magnitude": 0,
          "StopOnRemove": false
        },
        {
          "_EventType": "Remove",
          "Bounces": 0
        }
      ]
    },
    {
      "ConditionType": "Default",
      "Hitpoints": 0,
      "Element": "All",
      "Threshold": 0,
      "Time": 0,
      "Repeat": true,
      "Events": [
        {
          "_EventType": "Sound",
          "Bank": "Additional",
          "Cue": "woot_humidity_fire",
          "Magnitude": 0,
          "StopOnRemove": false
        },
        {
          "_EventType": "Effect",
          "Follow": true,
          "WorldAligned": false,
          "Effect": "weapon_woot_humidity_dispenser_water_projectile"
        }
      ]
    }
  ],
  "Scale": 1,
  "Model": "..\\..\\..\\Models\\Items_Wizard\\weapon_woot_humidity_dispenser_0",
  "Auras": []
}