{
  "Name": "weapon_gadget_remote_lighter",
  "LocalizedName": "#item_gadget_weapon04",
  "LocalizedDescription": "#item_gadget_weapon04d",
  "Sounds": [],
  "Grabbable": true,
  "Bound": false,
  "BlockStrength": 500,
  "WeaponClass": "Handgun",
  "CooldownTime": 1,
  "HideModel": false,
  "HideEffects": false,
  "PauseSounds": false,
  "Resistances": [],
  "PassiveAbilityType": "None",
  "PassiveAbilityStrength": 0,
  "Effects": [],
  "Lights": [],
  "HasSpecialAbility": false,
  "SpecialAbilityCooldown": 0,
  "SpecialAbility": null,
  "MeleeRange": 0,
  "MeleeMultihit": false,
  "MeleeConditions": [],
  "RangedRange": 15,
  "Facing": true,
  "Homing": 0,
  "RangedElevation": 0,
  "RangedDanger": 2,
  "GunRange": 0,
  "GunClip": 1,
  "GunRate": 1,
  "GunAccuracy": 1,
  "GunSound": "",
  "GunMuzzleEffect": "",
  "GunShellEffect": "",
  "GunTracerVelocity": 100,
  "GunNonTracer": "",
  "GunTracer": "",
  "GunConditions": [],
  "ProjectileModel": "..\\..\\..\\Models\\missiles\\mortar_round_0",
  "RangedConditions": [
    {
      "ConditionType": "Hit",
      "Hitpoints": 0,
      "Element": "All",
      "Threshold": 0,
      "Time": 0,
      "Repeat": true,
      "Events": [
        {
          "_EventType": "Damage",
          "AttackProperty": "Damage",
          "Element": "Fire",
          "Amount": 70,
          "Magnitude": 1,
          "VelocityBased": false
        },
        {
          "_EventType": "Damage",
          "AttackProperty": "Status",
          "Element": "Fire",
          "Amount": 5,
          "Magnitude": 1,
          "VelocityBased": false
        },
        {
          "_EventType": "Splash",
          "AttackProperty": "Damage",
          "Element": "Fire",
          "Amount": 4,
          "Magnitude": 1,
          "Radius": 3.5
        },
        {
          "_EventType": "Light",
          "Radius": 3,
          "DiffuseColor": [
            0.1,
            0,
            0
          ],
          "AmbientColor": [
            0.1,
            0,
            0
          ],
          "SpecularAmount": 1,
          "LightVariationType": "None",
          "VariationAmount": 0,
          "VariationSpeed": 0
        },
        {
          "_EventType": "Sound",
          "Bank": "Spells",
          "Cue": "spell_fire_force",
          "Magnitude": 0,
          "StopOnRemove": false
        },
        {
          "_EventType": "Effect",
          "Follow": false,
          "WorldAligned": false,
          "Effect": "gyrojet_hit"
        },
        {
          "_EventType": "Remove",
          "Bounces": 0
        }
      ]
    },
    {
      "ConditionType": "Collision",
      "Hitpoints": 0,
      "Element": "All",
      "Threshold": 10,
      "Time": 0,
      "Repeat": true,
      "Events": [
        {
          "_EventType": "Sound",
          "Bank": "Spells",
          "Cue": "spell_fire_hit",
          "Magnitude": 0,
          "StopOnRemove": false
        },
        {
          "_EventType": "Effect",
          "Follow": false,
          "WorldAligned": false,
          "Effect": "gyrojet_hit"
        },
        {
          "_EventType": "Splash",
          "AttackProperty": "Damage",
          "Element": "Fire",
          "Amount": 4,
          "Magnitude": 1,
          "Radius": 3.5
        },
        {
          "_EventType": "Splash",
          "AttackProperty": "Status",
          "Element": "Fire",
          "Amount": 2,
          "Magnitude": 1,
          "Radius": 1
        },
        {
          "_EventType": "Remove",
          "Bounces": 5
        }
      ]
    },
    {
      "ConditionType": "Default",
      "Hitpoints": 0,
      "Element": "All",
      "Threshold": 0,
      "Time": 0,
      "Repeat": true,
      "Events": [
        {
          "_EventType": "Sound",
          "Bank": "Spells",
          "Cue": "spell_fire_force",
          "Magnitude": 0,
          "StopOnRemove": false
        },
        {
          "_EventType": "Sound",
          "Bank": "Additional",
          "Cue": "wep_nagant_fire",
          "Magnitude": 0,
          "StopOnRemove": false
        },
        {
          "_EventType": "Effect",
          "Follow": true,
          "WorldAligned": false,
          "Effect": "gadget_remote_lighter_trail"
        }
      ]
    },
    {
      "ConditionType": "Timer",
      "Hitpoints": 0,
      "Element": "All",
      "Threshold": 0,
      "Time": 1.5,
      "Repeat": true,
      "Events": [
        {
          "_EventType": "Splash",
          "AttackProperty": "Damage",
          "Element": "Fire",
          "Amount": 4,
          "Magnitude": 1,
          "Radius": 3.5
        },
        {
          "_EventType": "Splash",
          "AttackProperty": "Status",
          "Element": "Fire",
          "Amount": 2,
          "Magnitude": 1,
          "Radius": 1
        },
        {
          "_EventType": "Sound",
          "Bank": "Spells",
          "Cue": "spell_fire_hit",
          "Magnitude": 0,
          "StopOnRemove": false
        },
        {
          "_EventType": "Effect",
          "Follow": false,
          "WorldAligned": false,
          "Effect": "gyrojet_hit"
        },
        {
          "_EventType": "Remove",
          "Bounces": 0
        }
      ]
    }
  ],
  "Scale": 1,
  "Model": "..\\..\\..\\Models\\Items_Wizard\\weapon_gadget_remote_lighter_0",
  "Auras": []
}